{
  "_class": "group",
  "booleanOperation": -1,
  "clippingMaskMode": 0,
  "do_objectID": "89AE3780-B560-4527-98F0-5D0B59068948",
  "exportOptions": {
    "_class": "exportOptions",
    "exportFormats": [
    ],
    "includedLayerIds": [
    ],
    "layerOptions": 0,
    "shouldTrim": false
  },
  "frame": {
    "_class": "rect",
    "constrainProportions": false,
    "height": 75,
    "width": 159,
    "x": 31,
    "y": 254
  },
  "hasClickThrough": false,
  "hasClippingMask": false,
  "isFixedToViewport": false,
  "isFlippedHorizontal": false,
  "isFlippedVertical": false,
  "isLocked": false,
  "isVisible": true,
  "layerListExpandedType": 0,
  "layers": [
    {
      "class": "text",
      "id": "74F48562-AABF-48BD-AA23-E92F5B7A928F"
    },
    {
      "class": "text",
      "id": "1FC3A635-6658-41B2-8B52-56F75A11A202"
    },
    {
      "class": "text",
      "id": "E0DE6AA5-6D48-41CD-9564-CAC7FFF579BA"
    }
  ],
  "name": "Stacked Group",
  "nameIsFixed": false,
  "resizingConstraint": 63,
  "resizingType": 0,
  "rotation": 0,
  "shouldBreakMaskChain": false,
  "style": {
    "_class": "style",
    "endMarkerType": 0,
    "miterLimit": 10,
    "startMarkerType": 0,
    "windingRule": 1
  },
  "userInfo": {
    "com.animaapp.stc-sketch-plugin": {
      "kModelPropertiesKey": {
        "align": 2,
        "isCollapsing": 1,
        "spacing": 6,
        "stackType": 0
      },
      "kViewTypeKey": "ADModelStackView"
    }
  }
}