{
  "_class": "text",
  "attributedString": {
    "_class": "attributedString",
    "attributes": [
      {
        "_class": "stringAttribute",
        "attributes": {
          "MSAttributedStringColorAttribute": {
            "_class": "color",
            "alpha": 1,
            "blue": 0.2156862745098039,
            "green": 0.196078431372549,
            "red": 0.196078431372549
          },
          "MSAttributedStringFontAttribute": {
            "_class": "fontDescriptor",
            "attributes": {
              "name": "Heebo-Medium",
              "size": 18
            }
          },
          "paragraphStyle": {
            "_class": "paragraphStyle",
            "alignment": 0
          },
          "textStyleVerticalAlignmentKey": 0
        },
        "length": 12,
        "location": 0
      }
    ],
    "string": "Kantor Pusat"
  },
  "automaticallyDrawOnUnderlyingPath": false,
  "booleanOperation": -1,
  "clippingMaskMode": 0,
  "do_objectID": "5CF9AED4-7AA9-41F2-9CFE-45CB5ACE4345",
  "dontSynchroniseWithSymbol": false,
  "exportOptions": {
    "_class": "exportOptions",
    "do_objectID": "8DCF34E3-94FD-49A8-85C3-5F3B0648891C",
    "exportFormats": [
    ],
    "includedLayerIds": [
    ],
    "layerOptions": 0,
    "shouldTrim": false
  },
  "frame": {
    "_class": "rect",
    "constrainProportions": false,
    "do_objectID": "0E9EC159-974B-4152-B406-EB9996F0D263",
    "height": 27,
    "width": 105,
    "x": 12,
    "y": 13
  },
  "glyphBounds": "{{1, 6}, {104, 14}}",
  "hasClippingMask": false,
  "isFixedToViewport": false,
  "isFlippedHorizontal": false,
  "isFlippedVertical": false,
  "isLocked": false,
  "isVisible": true,
  "layerListExpandedType": 0,
  "lineSpacingBehaviour": 2,
  "name": "Kantor Pusat",
  "nameIsFixed": false,
  "resizingConstraint": 47,
  "resizingType": 0,
  "rotation": 0,
  "shouldBreakMaskChain": false,
  "style": {
    "_class": "style",
    "do_objectID": "8484CC61-E664-4E47-B3F0-E5102CE5EA2A",
    "endMarkerType": 0,
    "miterLimit": 10,
    "startMarkerType": 0,
    "textStyle": {
      "_class": "textStyle",
      "do_objectID": "2A4CA9BC-E7D4-4627-BB41-C4A3325B989A",
      "encodedAttributes": {
        "MSAttributedStringColorAttribute": {
          "_class": "color",
          "alpha": 1,
          "blue": 0.2156862745098039,
          "green": 0.196078431372549,
          "red": 0.196078431372549
        },
        "MSAttributedStringFontAttribute": {
          "_class": "fontDescriptor",
          "attributes": {
            "name": "Heebo-Medium",
            "size": 18
          }
        },
        "paragraphStyle": {
          "_class": "paragraphStyle",
          "alignment": 0
        },
        "textStyleVerticalAlignmentKey": 0
      },
      "verticalAlignment": 0
    },
    "windingRule": 1
  },
  "textBehaviour": 0,
  "userInfo": {
    "com.animaapp.stc-sketch-plugin": {
      "kModelPropertiesKey": {
        "isAutoWidth": 1
      }
    }
  }
}