{
  "_class": "symbolInstance",
  "booleanOperation": -1,
  "clippingMaskMode": 0,
  "do_objectID": "B1A88409-CAE0-48D6-A3CD-2116599CB58D",
  "exportOptions": {
    "_class": "exportOptions",
    "do_objectID": "2CACB633-EF98-4D86-B40C-412534B9FD7B",
    "exportFormats": [
    ],
    "includedLayerIds": [
    ],
    "layerOptions": 0,
    "shouldTrim": false
  },
  "frame": {
    "_class": "rect",
    "constrainProportions": false,
    "do_objectID": "673A2992-038A-462A-8F7A-E503239B96AD",
    "height": 10,
    "width": 10,
    "x": 347,
    "y": 527
  },
  "hasClippingMask": false,
  "horizontalSpacing": 0,
  "isFixedToViewport": false,
  "isFlippedHorizontal": false,
  "isFlippedVertical": false,
  "isLocked": false,
  "isVisible": true,
  "layerListExpandedType": 0,
  "name": "Solid/filter",
  "nameIsFixed": false,
  "overrideValues": [
    {
      "_class": "overrideValue",
      "do_objectID": "C9088F9F-4DCD-4073-A525-EDD7C6E6AD98",
      "overrideName": "581DFBC9-578E-4E83-82AE-31CC4195B226/EC3AF79A-3C8F-4786-B869-9A2750B13BB5_layerStyle",
      "value": "5E919877-A4C1-45B1-BBC1-B500608C7D02"
    }
  ],
  "resizingConstraint": 63,
  "resizingType": 0,
  "rotation": 0,
  "scale": 0.4166666666666666,
  "shouldBreakMaskChain": false,
  "style": {
    "_class": "style",
    "blur": {
      "_class": "blur",
      "center": "{0.5, 0.5}",
      "do_objectID": "24FED41B-B0E3-4F6E-BC18-D30AD3BE0316",
      "isEnabled": false,
      "motionAngle": 0,
      "radius": 4.166666666666666,
      "saturation": 1,
      "type": 0
    },
    "do_objectID": "C9683E1B-A1FA-47A9-88D2-92D63DE63B3E",
    "endMarkerType": 0,
    "miterLimit": 10,
    "startMarkerType": 0,
    "windingRule": 1
  },
  "symbolID": "4C74937C-8033-42E9-B52E-DBD3762C42A5",
  "userInfo": {
    "com.animaapp.stc-sketch-plugin": {
      "kModelPropertiesKey": {
      }
    }
  },
  "verticalSpacing": 0
}