{
  "_class": "group",
  "booleanOperation": -1,
  "clippingMaskMode": 0,
  "do_objectID": "B054BA5F-FCB0-48E1-9491-367A6E6C158F",
  "exportOptions": {
    "_class": "exportOptions",
    "do_objectID": "09D9920A-CAF2-46EC-B112-4DC2E753DCF2",
    "exportFormats": [
    ],
    "includedLayerIds": [
    ],
    "layerOptions": 0,
    "shouldTrim": false
  },
  "frame": {
    "_class": "rect",
    "constrainProportions": false,
    "do_objectID": "A371B094-AA7E-4218-80EF-4C889B0A1E3B",
    "height": 18,
    "width": 80,
    "x": 597,
    "y": 269
  },
  "hasClickThrough": false,
  "hasClippingMask": false,
  "isFixedToViewport": false,
  "isFlippedHorizontal": false,
  "isFlippedVertical": false,
  "isLocked": false,
  "isVisible": true,
  "layerListExpandedType": 0,
  "layers": [
    {
      "class": "symbolInstance",
      "id": "788C6320-5D8C-4C78-9B5A-B41732D20542"
    },
    {
      "class": "text",
      "id": "53D32879-A2A2-40AB-B59F-7647B1D025BE"
    }
  ],
  "name": "Stacked Group 4",
  "nameIsFixed": false,
  "resizingConstraint": 63,
  "resizingType": 0,
  "rotation": 0,
  "shouldBreakMaskChain": false,
  "style": {
    "_class": "style",
    "do_objectID": "4B4A30DF-4D89-41D9-BF28-F84B62B91B35",
    "endMarkerType": 0,
    "miterLimit": 10,
    "startMarkerType": 0,
    "windingRule": 1
  },
  "userInfo": {
    "com.animaapp.stc-sketch-plugin": {
      "kModelPropertiesKey": {
        "align": 0,
        "isCollapsing": 1,
        "spacing": 16,
        "stackType": 1
      },
      "kViewTypeKey": "ADModelStackView"
    }
  }
}