{
  "_class": "shapeGroup",
  "booleanOperation": -1,
  "clippingMaskMode": 0,
  "do_objectID": "B9296BA9-A910-4826-9A0D-AC683D72B1C8",
  "exportOptions": {
    "_class": "exportOptions",
    "do_objectID": "9775C6B5-52A0-443F-8B07-753840AA2F7B",
    "exportFormats": [
    ],
    "includedLayerIds": [
    ],
    "layerOptions": 0,
    "shouldTrim": false
  },
  "frame": {
    "_class": "rect",
    "constrainProportions": false,
    "do_objectID": "DF135877-19EC-492F-B84D-85207A4D585D",
    "height": 9.561702127659576,
    "width": 6.742146596858634,
    "x": 1.068062827225133,
    "y": 0.1340425531914881
  },
  "hasClickThrough": false,
  "hasClippingMask": false,
  "isFixedToViewport": false,
  "isFlippedHorizontal": false,
  "isFlippedVertical": false,
  "isLocked": false,
  "isVisible": true,
  "layerListExpandedType": 1,
  "layers": [
    {
      "class": "shapePath",
      "id": "5F4FB14D-162B-4485-8F91-3435536DF183"
    },
    {
      "class": "shapePath",
      "id": "B72AF88B-B3D5-41EC-A47A-168979FD51B2"
    }
  ],
  "name": "Shape",
  "nameIsFixed": false,
  "resizingConstraint": 63,
  "resizingType": 0,
  "rotation": 0,
  "shouldBreakMaskChain": false,
  "style": {
    "_class": "style",
    "blur": {
      "_class": "blur",
      "center": "{0.5, 0.5}",
      "do_objectID": "8EDFBD7A-BF6D-445A-8AFB-C0CFFC54CFDC",
      "isEnabled": false,
      "motionAngle": 0,
      "radius": 2.225130890052356,
      "saturation": 1,
      "type": 0
    },
    "do_objectID": "3504D1C0-E962-4FF1-BD8F-6771D1D7FE69",
    "endMarkerType": 0,
    "fills": [
      {
        "_class": "fill",
        "color": {
          "_class": "color",
          "alpha": 1,
          "blue": 0.4,
          "green": 0,
          "red": 0.00392156862745098
        },
        "fillType": 0,
        "isEnabled": true,
        "noiseIndex": 0,
        "noiseIntensity": 0,
        "patternFillType": 1,
        "patternTileScale": 1
      }
    ],
    "miterLimit": 10,
    "startMarkerType": 0,
    "windingRule": 0
  },
  "windingRule": 0
}