{
  "_class": "symbolInstance",
  "booleanOperation": -1,
  "clippingMaskMode": 0,
  "do_objectID": "32CDFCF0-BEC9-4E02-B0E4-6965226C2013",
  "exportOptions": {
    "_class": "exportOptions",
    "do_objectID": "87113B90-2F9F-42D4-A509-4D65F0605F4A",
    "exportFormats": [
    ],
    "includedLayerIds": [
    ],
    "layerOptions": 0,
    "shouldTrim": false
  },
  "frame": {
    "_class": "rect",
    "constrainProportions": false,
    "do_objectID": "0468E698-2771-47A2-A842-2A93273A417E",
    "height": 36,
    "width": 102,
    "x": 1175,
    "y": 115
  },
  "hasClippingMask": false,
  "horizontalSpacing": 0,
  "isFixedToViewport": false,
  "isFlippedHorizontal": false,
  "isFlippedVertical": false,
  "isLocked": false,
  "isVisible": true,
  "layerListExpandedType": 0,
  "name": "Form Elements / Button / Auto / Normal",
  "nameIsFixed": false,
  "overrideValues": [
    {
      "_class": "overrideValue",
      "do_objectID": "21F88704-3947-4BFB-837A-D55173353F5E",
      "overrideName": "5C258BF6-CCC1-468B-A025-6D9A0ABCD804_stringValue",
      "value": "Edit Form"
    }
  ],
  "resizingConstraint": 63,
  "resizingType": 0,
  "rotation": 0,
  "scale": 1,
  "shouldBreakMaskChain": false,
  "style": {
    "_class": "style",
    "do_objectID": "22BF2B3B-9A53-4A0E-A9E4-640861FC2EF6",
    "endMarkerType": 0,
    "miterLimit": 10,
    "startMarkerType": 0,
    "windingRule": 1
  },
  "symbolID": "255EEB5D-0DB3-4725-94FF-998F12D4586A",
  "userInfo": {
    "com.animaapp.stc-sketch-plugin": {
      "kModelPropertiesKey": {
      }
    }
  },
  "verticalSpacing": 0
}